msftool/__init__.py
msftool/__main__.py
msftool/cli.py
msftool/packer.py
msftool/unpacker.py
mpm_msftool-1.0.0.dist-info/COPYING
mpm_msftool-1.0.0.dist-info/METADATA
mpm_msftool-1.0.0.dist-info/WHEEL
mpm_msftool-1.0.0.dist-info/entry_points.txt
mpm_msftool-1.0.0.dist-info/top_level.txt
mpm_msftool-1.0.0.dist-info/RECORD
